<?xml version='1.0' encoding='windows-1252' standalone='yes'?>
<MetaData>
<ProjectTemplate>
  <Title localize="yes">Tag Bus Module</Title>
  <Description localize="yes">Creates a sample tag bus module project containing a runtime and configuration class.</Description>
  <Filters localize="yes">TBDF:Modules</Filters>
  <Keywords localize="yes">tag;bus;module;framework;mapping;access;plugin</Keywords>
  <LocationPath>tag bus module sample project</LocationPath>
  <ProjectPath>Sample Tag Bus Module.lvproj</ProjectPath>
  <ListboxImagePath>images/datacomp.png</ListboxImagePath>
  <DocumentationPath>documentation/tag bus module doc.html</DocumentationPath>
  <CustomVIMode>AfterPage2NoUI</CustomVIMode>
  <CustomVIPath>scripting/PostCopyScripting.vi</CustomVIPath>
  <MetaDataClass>scripting/DecideModuleFeatures.lvclass</MetaDataClass> 
  <SortPriority>300</SortPriority>
</ProjectTemplate>
</MetaData>
